{"pageProps":{"post":[{"Paal":"பொருட்பால்","Adhigaram":"வலியறிதல் ","AdhigaramNumber":"48.5","Kural":"பீலிபெய் சாகாடும் அச்சிறும் அப்பண்டஞ்<br />சால மிகுத்துப் பெயின்.","Transliteration":"Peelipey Saakaatum  Achchirum  Appantanjjch  Aala  Mikuththup  Peyin","Vilakam":"மயில் இறகாக இருந்தாலும்கூட அதிகமாக ஏற்றப்பட்டால் வண்டியின் அச்சு முரிகின்ற அளவுக்கு அதற்குப் பலம் வந்து விடும்","Couplet":"With peacock feathers light, you load the wain;  Yet, heaped too high, the axle snaps in twain","kalaingar_urai":"மயில்  இறகாக  இருந்தாலும்கூட அதிகமாக ஏற்றப்பட்டால் வண்டியின்<br>அச்சு முரிகின்ற அளவுக்கு அதற்குப் பலம் வந்து விடும்.","parimezhalagar_urai":"பீலிபெய் சாகாடும் அச்சு இறும் - பீலியேற்றிய சகடமும் அச்சு முரியும், அப்பண்டம் சால மிகுத்துப் பெயின் - அப்பீலியை அது பொறுக்கும் அளவின்றி மிகுத்து ஏற்றின். (உம்மை சாகாட்டது வலிச்சிறப்பேயு மன்றிப் பீலியது நொய்மைச் சிறப்பும் தோன்ற நின்றது. 'இறும்' என்னுஞ் சினைவினை முதல்மேல் நின்றது. 'எளியர்' என்று பலரோடு பகைகொள்வான், தான் வலியனே ஆயினும் அவர் தொக்கவழி வலியழியும் , என்னும் பொருள் தோன்ற நின்றமையின் இது பிறிது மொழிதல் என்னும் அலங்காரம். இதனை 'நுவலா நுவற்சி' என்பாரும், 'ஒட்டு' என்பாரும்உளர். ஒருவன் தொகுவார் பலரோடு பகைகொள்ளற்க என்றமையின், இதனால் மாற்றான் வலியும் அவன் துணை வலியும் அறியா வழிப்படும் இழுக்குக் கூறப்பட்டது.)","m_varadharajanar":"மயிலிறகு ஏற்றிய வண்டியே ஆனாலும் , அந்த பண்டமும் (அளவோடு ஏற்றாமல்) அளவு கடந்து மிகுதியாக ஏற்றினால் அச்சு முறியும்.","Solomon_pappaiya":"மயில்தோகைதானே என்று அதை அளவுக்கு அதிகமாக வண்டியில் ஏற்றினால் வண்டியின் அச்சு முறிந்துபோகும்."}]},"__N_SSP":true}