{"pageProps":{"post":[{"Paal":"பொருட்பால்","Adhigaram":"சுற்றந்தழால் ","AdhigaramNumber":"53.4","Kural":"சுற்றத்தால் சுற்றப் படஒழுகல் செல்வந்தான்<br />பெற்றத்தால் பெற்ற பயன்.","Transliteration":"Sutraththaal Sutrap  Pataozhukal  Selvandhaan  Petraththaal  Petra  Payan","Vilakam":"தன் இனத்தார், அன்புடன் தன்னைச் சூழ்ந்து நிற்க வாழும் வாழ்க்கையே ஒருவன் பெற்ற செல்வத்தினால் கிடைத்திடும் பயனாகும்","Couplet":"The profit gained by wealth's increase,  Is living compassed round by relatives in peace","kalaingar_urai":"தன்    இனத்தார், அன்புடன் தன்னைச்   சூழ்ந்து   நிற்க வாழும் வாழ்க்கையே ஒருவன் பெற்ற செல்வத்தினால் கிடைத்திடும் பயனாகும்.","parimezhalagar_urai":"செல்வம் பெற்றத்தால் பெற்ற பயன் - செல்வம் பெற்ற அதனால் ஒருவன் பெற்ற பயனாவது, சுற்றத்தால் தான் சுற்றப்பட ஒழுகல் - தன் சுற்றத்தால் தான் சூழப்படும் வகை அதனைத் தழீஇ ஒழுகுதல். (பெற்ற என்பதனுள் அகரமும் அதனான் என்பதனுள் அன்சாரியையும்தொடைநோக்கி விகாரத்தால் தொக்கன. இவ் வொழுக்குப்பகையின்றி அரசாள்தற்கு ஏதுவாகலின், இதனைச் செல்வத்திற்குப்பயன் என்றார். இவை மூன்று பாட்டானும் சுற்றந் தழால்செல்வத்திற்கு ஏதுவும் அரணும் பயனும் ஆம் என்பதுகூறப்பட்டது.)","m_varadharajanar":"தக்கவழியில் செய்யப்படாத முயற்சி பலர் துணையாக நின்று(அதை முடிக்குமாறு) காத்த போதிலும் குறையாகிவிடும்.","Solomon_pappaiya":"தன் சுற்றத்தால் தான் சூழப்படும்படி அவர்களைத் தழுவி வாழ்வதே ஒருவன் செல்வத்தைப் பெற்றதன் பயன் ஆகும்."}]},"__N_SSP":true}